ds_fastapi_middleware/__init__.py
ds_fastapi_middleware/errors/__init__.py
ds_fastapi_middleware/errors/_exceptions.py
ds_fastapi_middleware/errors/_webapp.py
ds_fastapi_middleware/middlewares/__init__.py
ds_fastapi_middleware/middlewares/audit.py
ds_fastapi_middleware/middlewares/ctx.py
ds_fastapi_middleware/middlewares/timeout.py
ds_fastapi_middleware/middlewares/usage.py
ds_fastapi_middleware/models/__init__.py
ds_fastapi_middleware/models/audit.py
ds_fastapi_middleware/models/usage.py
ds_fastapi_middleware/utils/__init__.py
ds_fastapi_middleware/utils/dependency_injection.py
ds_fastapi_middleware/utils/internal_traffic.py
ds_fastapi_middleware/utils/authorization/__init__.py
ds_fastapi_middleware/utils/authorization/_context.py
ds_fastapi_middleware/utils/aws/__init__.py
ds_fastapi_middleware/utils/aws/client_factory.py
ds_fastapi_middleware/utils/aws/sqs.py
ds_fastapi_middleware/utils/log/__init__.py
ds_fastapi_middleware/utils/log/audit.py
ds_fastapi_middleware/utils/log/stdout.py
ds_fastapi_middleware/utils/usage/__init__.py
ds_fastapi_middleware/utils/usage/write.py
tests/__init__.py
tests/test_middleware_audit.py
tests/test_middleware_ctx.py
tests/test_middleware_timeout.py
tests/test_middleware_usage.py
tests/test_utils_log_stdout.py
ds_fastapi_middleware-2024.4.2.dist-info/LICENSE
ds_fastapi_middleware-2024.4.2.dist-info/METADATA
ds_fastapi_middleware-2024.4.2.dist-info/WHEEL
ds_fastapi_middleware-2024.4.2.dist-info/top_level.txt
ds_fastapi_middleware-2024.4.2.dist-info/RECORD
