Metadata-Version: 2.1
Name: ds_fastapi_middleware
Version: 2024.4.2
Summary: A Python package for FastAPI middleware. Pacakge is part of the greater GraspDP / DPW project.
Author-email: yuan1989 <yuan@grasplabs.no>, skerve <arve.skjervheim@gmail.com>
Maintainer-email: skerve <arve.skjervheim@gmail.com>
License: MIT License
Project-URL: Homepage, https://github.com/grasp-labs/ds-fastapi-middleware
Project-URL: Documentation, https://github.com/grasp-labs/ds-fastapi-middleware
Project-URL: Repository, https://github.com/grasp-labs/ds-fastapi-middleware
Project-URL: Issues, https://github.com/grasp-labs/ds-fastapi-middleware/issues
Project-URL: Changelog, https://github.com/grasp-labs/ds-fastapi-middleware/blob/main/CHANGELOG.md
Keywords: grasp-labs,python,fastApi,middleware,aws
Classifier: Development Status :: 4 - Beta
Classifier: Programming Language :: Python
Requires-Python: >=3.8
License-File: LICENSE
Requires-Dist: boto3
Requires-Dist: fastapi
Requires-Dist: requests
